docs/Makefile
docs/advanced_usage.rst
docs/conf.py
docs/convert_to_vgsl_spec.rst
docs/getting_started.rst
docs/index.rst
docs/installation.rst
docs/introduction.rst
docs/make.bat
docs/supported_layers.rst
docs/tutorials.rst
docs/_static/_sphinx_javascript_frameworks_compat.js
docs/_static/basic.css
docs/_static/doctools.js
docs/_static/documentation_options.js
docs/_static/file.png
docs/_static/jquery.js
docs/_static/language_data.js
docs/_static/minus.png
docs/_static/plus.png
docs/_static/pygments.css
docs/_static/searchtools.js
docs/_static/sphinx_highlight.js
docs/_static/css/badge_only.css
docs/_static/css/theme.css
docs/_static/css/fonts/Roboto-Slab-Bold.woff
docs/_static/css/fonts/Roboto-Slab-Bold.woff2
docs/_static/css/fonts/Roboto-Slab-Regular.woff
docs/_static/css/fonts/Roboto-Slab-Regular.woff2
docs/_static/css/fonts/fontawesome-webfont.eot
docs/_static/css/fonts/fontawesome-webfont.svg
docs/_static/css/fonts/fontawesome-webfont.ttf
docs/_static/css/fonts/fontawesome-webfont.woff
docs/_static/css/fonts/fontawesome-webfont.woff2
docs/_static/css/fonts/lato-bold-italic.woff
docs/_static/css/fonts/lato-bold-italic.woff2
docs/_static/css/fonts/lato-bold.woff
docs/_static/css/fonts/lato-bold.woff2
docs/_static/css/fonts/lato-normal-italic.woff
docs/_static/css/fonts/lato-normal-italic.woff2
docs/_static/css/fonts/lato-normal.woff
docs/_static/css/fonts/lato-normal.woff2
docs/_static/js/badge_only.js
docs/_static/js/html5shiv-printshiv.min.js
docs/_static/js/html5shiv.min.js
docs/_static/js/theme.js
docs/source/vgslify.core.rst
docs/source/vgslify.model_parsers.rst
docs/source/vgslify.rst
docs/source/vgslify.tensorflow.rst
docs/source/vgslify.torch.rst
docs/source/vgslify.utils.rst
tests/test_core/test_parsers.py
tests/test_core/test_utils.py
tests/test_parser/test_tf_to_spec.py
tests/test_tensorflow/test_layer_factory.py
tests/test_utils/test_model_to_spec.py
vgslify/__init__.py
vgslify/_version.py
vgslify/generator.py
vgslify/core/__init__.py
vgslify-0.14.0.dist-info/LICENSE
vgslify-0.14.0.dist-info/METADATA
vgslify-0.14.0.dist-info/WHEEL
vgslify-0.14.0.dist-info/top_level.txt
vgslify-0.14.0.dist-info/RECORD
