Metadata-Version: 2.2
Name: vgslify
Version: 0.14.0
Summary: VGSLify is a Python toolkit for rapid prototyping and seamless conversion between TensorFlow and PyTorch models and VGSL.
Author-email: Tim Koornstra <tim.koornstra@gmail.com>
Project-URL: Homepage, https://github.com/TimKoornstra/VGSLify
Classifier: Programming Language :: Python :: 3
Classifier: License :: OSI Approved :: MIT License
Classifier: Operating System :: OS Independent
Requires-Python: >=3.9
License-File: LICENSE
Provides-Extra: torch
Requires-Dist: torch>=2.0; extra == "torch"
Provides-Extra: tensorflow
Requires-Dist: tensorflow>=2.14; extra == "tensorflow"
